anastasia_logging/__init__.py
anastasia_logging/codes/__init__.py
anastasia_logging/codes/standard.py
anastasia_logging/codes/standard_critical.py
anastasia_logging/codes/standard_debug.py
anastasia_logging/codes/standard_errors.py
anastasia_logging/codes/standard_info.py
anastasia_logging/codes/standard_warning.py
anastasia_logging/env/__init__.py
anastasia_logging/env/env_variables.py
anastasia_logging/logger.py
anastasia_logging-1.3.4.dist-info/METADATA
anastasia_logging-1.3.4.dist-info/WHEEL
anastasia_logging-1.3.4.dist-info/RECORD
