Metadata-Version: 2.1
Name: anastasia-logging
Version: 1.3.4
Summary: Anastasia Logging Standarization
Author: anastasiaai
Requires-Python: >=3.8,<4.0
Classifier: Programming Language :: Python :: 3
Classifier: Programming Language :: Python :: 3.8
Classifier: Programming Language :: Python :: 3.9
Classifier: Programming Language :: Python :: 3.10
Classifier: Programming Language :: Python :: 3.11
